{"3xsrKDabOfq8yURSDzvE0g==":"creaslim-452570-unsplash-2000x2500.jpg","5v3TY83ZFX27LSEI8PfPQw==":"max-lakutin-1559-unsplash-2000x1333.jpg","zc5GiXsQ1wAhYeeHP7a24A==":"tim-mossholder-635962-unsplash-2000x1333.jpg","9xfItbdAMntoVGz8dAno6A==":"pallet-1100x724.jpg","NHFRVLUmq6mnqSKSddqO1w==":"2-122x122.png","buLRWYqqVc88H6im/aOzvg==":"1-96x96.png","5NQ8UUqA/Ces9bc6q/+7Lg==":"2-96x96.png","9qxs1iaMnGid3/cmFwaTZg==":"2-500x500.png","X+fG9+BsdPvcjZRzt6WidA==":"palletable.co.uk-1042x1042.jpg","POYklOwDgw5fyDjR+kccGQ==":"palletable.co.uk-96x96.jpg","78jNo9FJBbTbzbEHlCGoXA==":"palletable.co.uk-122x122.jpg"}